{"data":[{"id":"MDU6SXNzdWU2MTE3NjU0MDA=","closed":false,"title":"pic of project","createdAt":"2020-05-04T10:25:40Z","url":"https://github.com/Hardikkhanesa/ToDoApp/issues/1","number":1,"assignees":{"nodes":[]},"repository":{"name":"ToDoApp","url":"https://github.com/Hardikkhanesa/ToDoApp","owner":{"login":"Hardikkhanesa","avatarUrl":"https://avatars0.githubusercontent.com/u/26074662?u=150498c31912eb48d49e2646ecd2b3c9cd8ecd61&v=4","url":"https://github.com/Hardikkhanesa"}}},{"id":"MDU6SXNzdWU0MjQxMzY5NzY=","closed":true,"title":"Kaizen2018","createdAt":"2019-03-22T10:19:50Z","url":"https://github.com/Hardikkhanesa/WebTechnology/issues/1","number":1,"assignees":{"nodes":[]},"repository":{"name":"WebTechnology","url":"https://github.com/Hardikkhanesa/WebTechnology","owner":{"login":"Hardikkhanesa","avatarUrl":"https://avatars0.githubusercontent.com/u/26074662?u=150498c31912eb48d49e2646ecd2b3c9cd8ecd61&v=4","url":"https://github.com/Hardikkhanesa"}}}],"open":1,"closed":1,"totalCount":2}